troposim/__init__.py
troposim/_types.py
troposim/analysis.py
troposim/constants.py
troposim/decorrelation.py
troposim/deramp.py
troposim/igrams.py
troposim/log.py
troposim/plotting.py
troposim/simulated_stack.py
troposim/stratified.py
troposim/turbulence.py
troposim/utils.py
troposim/deformation/__init__.py
troposim/deformation/geertsma.py
troposim/deformation/okada.py
troposim/deformation/synthetic.py
troposim-0.2.2.dist-info/licenses/LICENSE.txt
troposim-0.2.2.dist-info/METADATA
troposim-0.2.2.dist-info/WHEEL
troposim-0.2.2.dist-info/top_level.txt
troposim-0.2.2.dist-info/RECORD
