Metadata-Version: 2.4
Name: troposim
Version: 0.2.2
Summary: Simulate InSAR tropospheric noise
Author: scott
Author-email: scott.stanie@gmail.com
License: mit
Keywords: insar,simulation,troposphere,turbulence,remote-sensing,sar,synthetic-aperture-radar
Platform: any
Classifier: Development Status :: 4 - Beta
Classifier: Programming Language :: Python
Requires-Python: >=3.9
License-File: LICENSE.txt
Requires-Dist: numpy
Requires-Dist: scipy
Requires-Dist: tqdm
Requires-Dist: setuptools
Provides-Extra: testing
Requires-Dist: pytest; extra == "testing"
Dynamic: license-file
